port_lens/__init__.py
port_lens/__main__.py
port_lens/main.py
port_lens-0.7.dist-info/METADATA
port_lens-0.7.dist-info/WHEEL
port_lens-0.7.dist-info/entry_points.txt
port_lens-0.7.dist-info/top_level.txt
port_lens-0.7.dist-info/RECORD
