Metadata-Version: 2.1
Name: port-lens
Version: 0.7
Summary: A simple port scanner that works.
Home-page: https://github.com/1806exe/port-lens
Author: Inno Mgubhe
Author-email: 1806exe@email.com
License: MIT
